pkgdeps/__init__.py
pkgdeps-0.0.3.dist-info/DESCRIPTION.rst
pkgdeps-0.0.3.dist-info/METADATA
pkgdeps-0.0.3.dist-info/RECORD
pkgdeps-0.0.3.dist-info/WHEEL
pkgdeps-0.0.3.dist-info/entry_points.txt
pkgdeps-0.0.3.dist-info/metadata.json
pkgdeps-0.0.3.dist-info/top_level.txt
