Metadata-Version: 2.0
Name: pkgdeps
Version: 0.0.3
Summary: Explore dependencies of a Python package by parsing its imports.
Home-page: https://github.com/harto/pkgdeps
Author: Stuart Campbell
Author-email: stuart@harto.org
License: MIT
Keywords: python package dependency
Platform: UNKNOWN
